ownSync.py
ownSyncUtils.py
setup.py
ownSync.egg-info/PKG-INFO
ownSync.egg-info/SOURCES.txt
ownSync.egg-info/dependency_links.txt
ownSync.egg-info/requires.txt
ownSync.egg-info/top_level.txt