Metadata-Version: 1.1
Name: ownSync
Version: 0.6.0
Summary: Python ownCloud file sync utility
Home-page: https://github.com/lwahlmeier/ownSync
Author: Luke Wahlmeier
Author-email: lwahlmeier@gmail.com
License: BSD
Download-URL: https://github.com/lwahlmeier/ownSync/tarball/0.6.0
Keywords: owncloud files sync sychronize
Platform: UNKNOWN
Classifier: Development Status :: 4 - Beta
Classifier: Intended Audience :: End Users/Desktop
Classifier: Environment :: Console
Classifier: Topic :: Internet
Classifier: Natural Language :: English
Classifier: Operating System :: POSIX
Classifier: License :: OSI Approved :: BSD License
Classifier: Programming Language :: Python :: 2.6
Classifier: Programming Language :: Python :: 2.7
Classifier: Programming Language :: Python :: 3.5
Classifier: Programming Language :: Python :: 3.6
